alicat/__init__.py
alicat/driver.py
alicat/mock.py
alicat/py.typed
alicat/util.py
alicat-0.7.0.dist-info/LICENSE
alicat-0.7.0.dist-info/METADATA
alicat-0.7.0.dist-info/WHEEL
alicat-0.7.0.dist-info/entry_points.txt
alicat-0.7.0.dist-info/top_level.txt
alicat-0.7.0.dist-info/RECORD
