Metadata-Version: 2.1
Name: alicat
Version: 0.7.0
Summary: Python driver for Alicat mass flow controllers.
Author-email: Pat Fuller <patrickfuller@gmail.com>
Maintainer-email: Alex Ruddick <alex@ruddick.tech>
Project-URL: Homepage, https://github.com/alexrudd2/alicat
Project-URL: Issues, https://github.com/alexrudd2/alicat/issues
Classifier: License :: OSI Approved :: GNU General Public License v2 (GPLv2)
Classifier: Development Status :: 4 - Beta
Classifier: Natural Language :: English
Classifier: Programming Language :: Python
Classifier: Programming Language :: Python :: 3
Classifier: Programming Language :: Python :: 3.9
Classifier: Programming Language :: Python :: 3.10
Classifier: Programming Language :: Python :: 3.11
Classifier: Programming Language :: Python :: 3.12
Classifier: Programming Language :: Python :: 3.13
Classifier: Topic :: Scientific/Engineering :: Human Machine Interfaces
License-File: LICENSE
Requires-Dist: pyserial
Provides-Extra: test
Requires-Dist: mypy ==1.11.2 ; extra == 'test'
Requires-Dist: pytest <9,>=8 ; extra == 'test'
Requires-Dist: pytest-cov <6,>=5 ; extra == 'test'
Requires-Dist: pytest-asyncio >=0.23.5 ; extra == 'test'
Requires-Dist: pytest-xdist <4,>=3 ; extra == 'test'
Requires-Dist: ruff ==0.6.6 ; extra == 'test'
Requires-Dist: types-pyserial ; extra == 'test'
